{"v":"5.2.1","fr":24,"ip":0,"op":60,"w":1024,"h":1024,"nm":"clinking_glasses ","ddd":0,"assets":[{"id":"comp_0","layers":[{"ddd":0,"ind":1,"ty":4,"nm":"Glass Highlight","sr":1,"ks":{"o":{"a":0,"k":70,"ix":11},"r":{"a":0,"k":12,"ix":10},"p":{"a":0,"k":[764.097,500.69,0],"ix":2},"a":{"a":0,"k":[5.431,-0.999,0],"ix":1},"s":{"a":0,"k":[1400,1400,100],"ix":6}},"ao":0,"shapes":[{"ty":"gr","it":[{"ind":0,"ty":"sh","ix":1,"ks":{"a":0,"k":{"i":[[1.488,0.35],[-5.67,-5.719],[0.968,1.691],[0,0]],"o":[[0,0],[0.894,0.904],[-5.236,-9.126],[0,0]],"v":[[0.876,-11.146],[8.062,8.74],[9.697,7.867],[3.895,-11.308]],"c":true},"ix":2},"nm":"Path 1","mn":"ADBE Vector Shape - Group","hd":false},{"ty":"gf","o":{"a":0,"k":100,"ix":10},"r":1,"g":{"p":5,"k":{"a":0,"k":[0,1,1,1,0.057,1,1,1,0.114,1,1,1,0.557,1,1,1,1,1,1,1,0,0,0.057,0.057,0.114,0.114,0.557,0.557,1,1],"ix":9}},"s":{"a":0,"k":[8.163,10.024],"ix":5},"e":{"a":0,"k":[2.196,-11.453],"ix":6},"t":1,"nm":"highlight gradientazaezaezaezaeaze","mn":"ADBE Vector Graphic - G-Fill","hd":false},{"ty":"tr","p":{"a":0,"k":[0,0],"ix":2},"a":{"a":0,"k":[0,0],"ix":1},"s":{"a":0,"k":[100,100],"ix":3},"r":{"a":0,"k":0,"ix":6},"o":{"a":0,"k":100,"ix":7},"sk":{"a":0,"k":0,"ix":4},"sa":{"a":0,"k":0,"ix":5},"nm":"Transform"}],"nm":"Glass Highlight","np":2,"cix":2,"ix":1,"mn":"ADBE Vector Group","hd":false}],"ip":0,"op":60,"st":0,"bm":0},{"ddd":0,"ind":2,"ty":4,"nm":"BotShadow","sr":1,"ks":{"o":{"a":0,"k":100,"ix":11},"r":{"a":0,"k":12,"ix":10},"p":{"a":0,"k":[859.919,903.952,0],"ix":2},"a":{"a":0,"k":[18.114,25.753,0],"ix":1},"s":{"a":0,"k":[1400,1400,100],"ix":6}},"ao":0,"shapes":[{"ty":"gr","it":[{"ind":0,"ty":"sh","ix":1,"ks":{"a":0,"k":{"i":[[-0.673,-0.602],[0.154,-0.064]],"o":[[1.473,1.313],[-1.526,0.627]],"v":[[16.983,24.795],[19.392,26.705]],"c":true},"ix":2},"nm":"Path 1","mn":"ADBE Vector Shape - Group","hd":false},{"ty":"fl","c":{"a":0,"k":[0.588235318661,0.666666686535,0.690196096897,1],"ix":4},"o":{"a":0,"k":100,"ix":5},"r":1,"nm":"Fill 1","mn":"ADBE Vector Graphic - Fill","hd":false},{"ty":"tr","p":{"a":0,"k":[0,0],"ix":2},"a":{"a":0,"k":[0,0],"ix":1},"s":{"a":0,"k":[100,100],"ix":3},"r":{"a":0,"k":0,"ix":6},"o":{"a":0,"k":100,"ix":7},"sk":{"a":0,"k":0,"ix":4},"sa":{"a":0,"k":0,"ix":5},"nm":"Transform"}],"nm":"BotShadow","np":2,"cix":2,"ix":1,"mn":"ADBE Vector Group","hd":false}],"ip":0,"op":60,"st":0,"bm":0},{"ddd":0,"ind":3,"ty":4,"nm":"Bubble","sr":1,"ks":{"o":{"a":0,"k":100,"ix":11},"r":{"a":0,"k":12,"ix":10},"p":{"a":0,"k":[822.726,550.903,0],"ix":2},"a":{"a":0,"k":[10.272,1.639,0],"ix":1},"s":{"a":0,"k":[1400,1400,100],"ix":6}},"ao":0,"shapes":[{"ty":"gr","it":[{"ty":"gr","it":[{"ind":0,"ty":"sh","ix":1,"ks":{"a":0,"k":{"i":[[-0.17,-0.64],[0.171,0.642]],"o":[[0.174,0.645],[-0.173,-0.646]],"v":[[6.53,-2.326],[5.565,-2.064]],"c":true},"ix":2},"nm":"Path 1","mn":"ADBE Vector Shape - Group","hd":false},{"ty":"fl","c":{"a":0,"k":[1,0.909803926945,0.733333349228,1],"ix":4},"o":{"a":0,"k":100,"ix":5},"r":1,"nm":"Fill 1","mn":"ADBE Vector Graphic - Fill","hd":false},{"ty":"tr","p":{"a":1,"k":[{"i":{"x":0.667,"y":1},"o":{"x":0.333,"y":0},"n":"0p667_1_0p333_0","t":0,"s":[7.534,6.566],"e":[5.206,-1.669],"to":[-0.38799199461937,-1.37258994579315],"ti":[0,0]},{"i":{"x":0.667,"y":1},"o":{"x":0.333,"y":0},"n":"0p667_1_0p333_0","t":13,"s":[5.206,-1.669],"e":[7.534,6.566],"to":[0,0],"ti":[0,0]},{"i":{"x":0.667,"y":1},"o":{"x":0.333,"y":0},"n":"0p667_1_0p333_0","t":27,"s":[7.534,6.566],"e":[5.206,-1.669],"to":[0,0],"ti":[0.38799199461937,1.37258994579315]},{"t":40}],"ix":2},"a":{"a":0,"k":[6.048,-2.195],"ix":1},"s":{"a":1,"k":[{"i":{"x":[0.667,0.667],"y":[1,1]},"o":{"x":[0.333,0.333],"y":[0,0]},"n":["0p667_1_0p333_0","0p667_1_0p333_0"],"t":0,"s":[0,0],"e":[100,100]},{"i":{"x":[0.667,0.667],"y":[1,1]},"o":{"x":[0.333,0.333],"y":[0,0]},"n":["0p667_1_0p333_0","0p667_1_0p333_0"],"t":4,"s":[100,100],"e":[0,0]},{"i":{"x":[0.667,0.667],"y":[1,1]},"o":{"x":[0.333,0.333],"y":[0,0]},"n":["0p667_1_0p333_0","0p667_1_0p333_0"],"t":27,"s":[0,0],"e":[100,100]},{"t":31}],"ix":3},"r":{"a":0,"k":0,"ix":6},"o":{"a":1,"k":[{"i":{"x":[0.833],"y":[1]},"o":{"x":[0.333],"y":[0]},"n":["0p833_1_0p333_0"],"t":0,"s":[100],"e":[100]},{"i":{"x":[0.833],"y":[1]},"o":{"x":[0.167],"y":[0]},"n":["0p833_1_0p167_0"],"t":9,"s":[100],"e":[0]},{"i":{"x":[0.667],"y":[1]},"o":{"x":[0.167],"y":[0]},"n":["0p667_1_0p167_0"],"t":13,"s":[0],"e":[100]},{"i":{"x":[0.833],"y":[1]},"o":{"x":[0.333],"y":[0]},"n":["0p833_1_0p333_0"],"t":27,"s":[100],"e":[100]},{"i":{"x":[0.833],"y":[1]},"o":{"x":[0.167],"y":[0]},"n":["0p833_1_0p167_0"],"t":36,"s":[100],"e":[0]},{"t":40}],"ix":7},"sk":{"a":0,"k":0,"ix":4},"sa":{"a":0,"k":0,"ix":5},"nm":"Transform"}],"nm":"Group 1","np":2,"cix":2,"ix":1,"mn":"ADBE Vector Group","hd":false},{"ty":"gr","it":[{"ind":0,"ty":"sh","ix":1,"ks":{"a":0,"k":{"i":[[-0.346,-1.289],[0.344,1.288]],"o":[[0.345,1.285],[-0.344,-1.284]],"v":[[9.676,-0.253],[7.745,0.263]],"c":true},"ix":2},"nm":"Path 2","mn":"ADBE Vector Shape - Group","hd":false},{"ty":"fl","c":{"a":0,"k":[1,0.909803926945,0.733333349228,1],"ix":4},"o":{"a":0,"k":100,"ix":5},"r":1,"nm":"Fill 2","mn":"ADBE Vector Graphic - Fill","hd":false},{"ty":"tr","p":{"a":1,"k":[{"i":{"x":0.667,"y":1},"o":{"x":0.333,"y":0},"n":"0p667_1_0p333_0","t":5,"s":[11.48,8.192],"e":[8.561,-2.668],"to":[-0.48660373687744,-1.8100129365921],"ti":[0,0]},{"i":{"x":0.833,"y":1},"o":{"x":0.167,"y":0},"n":"0p833_1_0p167_0","t":18,"s":[8.561,-2.668],"e":[11.48,8.192],"to":[0,0],"ti":[0,0]},{"i":{"x":0.667,"y":1},"o":{"x":0.333,"y":0},"n":"0p667_1_0p333_0","t":38,"s":[11.48,8.192],"e":[8.561,-2.668],"to":[0,0],"ti":[0.48660373687744,1.8100129365921]},{"t":51}],"ix":2},"a":{"a":0,"k":[8.711,0.005],"ix":1},"s":{"a":1,"k":[{"i":{"x":[0.667,0.667],"y":[1,1]},"o":{"x":[0.333,0.333],"y":[0,0]},"n":["0p667_1_0p333_0","0p667_1_0p333_0"],"t":5,"s":[0,0],"e":[100,100]},{"i":{"x":[0.833,0.833],"y":[1,1]},"o":{"x":[0.167,0.167],"y":[0,0]},"n":["0p833_1_0p167_0","0p833_1_0p167_0"],"t":9,"s":[100,100],"e":[0,0]},{"i":{"x":[0.667,0.667],"y":[1,1]},"o":{"x":[0.333,0.333],"y":[0,0]},"n":["0p667_1_0p333_0","0p667_1_0p333_0"],"t":38,"s":[0,0],"e":[100,100]},{"t":42}],"ix":3},"r":{"a":0,"k":0,"ix":6},"o":{"a":1,"k":[{"i":{"x":[0.667],"y":[1]},"o":{"x":[0.333],"y":[0]},"n":["0p667_1_0p333_0"],"t":5,"s":[100],"e":[100]},{"i":{"x":[0.667],"y":[1]},"o":{"x":[0.333],"y":[0]},"n":["0p667_1_0p333_0"],"t":13,"s":[100],"e":[0]},{"i":{"x":[0.833],"y":[1]},"o":{"x":[0.167],"y":[0]},"n":["0p833_1_0p167_0"],"t":18,"s":[0],"e":[100]},{"i":{"x":[0.667],"y":[1]},"o":{"x":[0.333],"y":[0]},"n":["0p667_1_0p333_0"],"t":38,"s":[100],"e":[100]},{"i":{"x":[0.667],"y":[1]},"o":{"x":[0.333],"y":[0]},"n":["0p667_1_0p333_0"],"t":46,"s":[100],"e":[0]},{"t":51}],"ix":7},"sk":{"a":0,"k":0,"ix":4},"sa":{"a":0,"k":0,"ix":5},"nm":"Transform"}],"nm":"Group 2","np":2,"cix":2,"ix":2,"mn":"ADBE Vector Group","hd":false},{"ty":"gr","it":[{"ind":0,"ty":"sh","ix":1,"ks":{"a":0,"k":{"i":[[-0.255,-0.958],[0.261,0.972]],"o":[[0.262,0.971],[-0.258,-0.963]],"v":[[7.888,1.773],[6.441,2.164]],"c":true},"ix":2},"nm":"Path 3","mn":"ADBE Vector Shape - Group","hd":false},{"ty":"fl","c":{"a":0,"k":[1,0.909803926945,0.733333349228,1],"ix":4},"o":{"a":0,"k":100,"ix":5},"r":1,"nm":"Fill 3","mn":"ADBE Vector Graphic - Fill","hd":false},{"ty":"tr","p":{"a":1,"k":[{"i":{"x":0.667,"y":1},"o":{"x":0.333,"y":0},"n":"0p667_1_0p333_0","t":10,"s":[9.932,8.303],"e":[5.822,-2.61],"to":[-0.68493926525116,-1.81886923313141],"ti":[0,0]},{"i":{"x":0.833,"y":1},"o":{"x":0.167,"y":0},"n":"0p833_1_0p167_0","t":28,"s":[5.822,-2.61],"e":[9.932,8.303],"to":[0,0],"ti":[0,0]},{"i":{"x":0.667,"y":1},"o":{"x":0.333,"y":0},"n":"0p667_1_0p333_0","t":42,"s":[9.932,8.303],"e":[5.822,-2.61],"to":[0,0],"ti":[0.68493926525116,1.81886923313141]},{"t":60}],"ix":2},"a":{"a":0,"k":[7.165,1.973],"ix":1},"s":{"a":1,"k":[{"i":{"x":[0.667,0.667],"y":[1,1]},"o":{"x":[0.333,0.333],"y":[0,0]},"n":["0p667_1_0p333_0","0p667_1_0p333_0"],"t":10,"s":[0,0],"e":[100,100]},{"i":{"x":[0.833,0.833],"y":[1,1]},"o":{"x":[0.167,0.167],"y":[0,0]},"n":["0p833_1_0p167_0","0p833_1_0p167_0"],"t":15,"s":[100,100],"e":[0,0]},{"i":{"x":[0.667,0.667],"y":[1,1]},"o":{"x":[0.333,0.333],"y":[0,0]},"n":["0p667_1_0p333_0","0p667_1_0p333_0"],"t":42,"s":[0,0],"e":[100,100]},{"t":47}],"ix":3},"r":{"a":0,"k":0,"ix":6},"o":{"a":1,"k":[{"i":{"x":[0.667],"y":[1]},"o":{"x":[0.333],"y":[0]},"n":["0p667_1_0p333_0"],"t":10,"s":[100],"e":[100]},{"i":{"x":[0.667],"y":[1]},"o":{"x":[0.333],"y":[0]},"n":["0p667_1_0p333_0"],"t":23,"s":[100],"e":[0]},{"i":{"x":[0.833],"y":[1]},"o":{"x":[0.167],"y":[0]},"n":["0p833_1_0p167_0"],"t":28,"s":[0],"e":[100]},{"i":{"x":[0.667],"y":[1]},"o":{"x":[0.333],"y":[0]},"n":["0p667_1_0p333_0"],"t":42,"s":[100],"e":[100]},{"i":{"x":[0.667],"y":[1]},"o":{"x":[0.333],"y":[0]},"n":["0p667_1_0p333_0"],"t":55,"s":[100],"e":[0]},{"t":60}],"ix":7},"sk":{"a":0,"k":0,"ix":4},"sa":{"a":0,"k":0,"ix":5},"nm":"Transform"}],"nm":"Group 3","np":2,"cix":2,"ix":3,"mn":"ADBE Vector Group","hd":false},{"ty":"gr","it":[{"ind":0,"ty":"sh","ix":1,"ks":{"a":0,"k":{"i":[[-0.433,-1.601],[0.434,1.614]],"o":[[0.431,1.617],[-0.427,-1.605]],"v":[[10.719,5.078],[8.3,5.726]],"c":true},"ix":2},"nm":"Path 4","mn":"ADBE Vector Shape - Group","hd":false},{"ty":"fl","c":{"a":0,"k":[1,0.909803926945,0.733333349228,1],"ix":4},"o":{"a":0,"k":100,"ix":5},"r":1,"nm":"Fill 4","mn":"ADBE Vector Graphic - Fill","hd":false},{"ty":"tr","p":{"a":1,"k":[{"i":{"x":0.667,"y":1},"o":{"x":0.333,"y":0},"n":"0p667_1_0p333_0","t":19,"s":[10.739,8.574],"e":[8.188,-3.304],"to":[-0.42517173290253,-1.97954058647156],"ti":[0.42517173290253,1.97954058647156]},{"t":43}],"ix":2},"a":{"a":0,"k":[9.51,5.407],"ix":1},"s":{"a":1,"k":[{"i":{"x":[0.667,0.667],"y":[1,1]},"o":{"x":[0.333,0.333],"y":[0,0]},"n":["0p667_1_0p333_0","0p667_1_0p333_0"],"t":19,"s":[0,0],"e":[100,100]},{"t":27}],"ix":3},"r":{"a":0,"k":0,"ix":6},"o":{"a":1,"k":[{"i":{"x":[0.667],"y":[1]},"o":{"x":[0.333],"y":[0]},"n":["0p667_1_0p333_0"],"t":19,"s":[100],"e":[100]},{"i":{"x":[0.667],"y":[1]},"o":{"x":[0.333],"y":[0]},"n":["0p667_1_0p333_0"],"t":37,"s":[100],"e":[0]},{"t":43}],"ix":7},"sk":{"a":0,"k":0,"ix":4},"sa":{"a":0,"k":0,"ix":5},"nm":"Transform"}],"nm":"Group 4","np":2,"cix":2,"ix":4,"mn":"ADBE Vector Group","hd":false},{"ty":"tr","p":{"a":0,"k":[0,0],"ix":2},"a":{"a":0,"k":[0,0],"ix":1},"s":{"a":0,"k":[100,100],"ix":3},"r":{"a":0,"k":0,"ix":6},"o":{"a":0,"k":100,"ix":7},"sk":{"a":0,"k":0,"ix":4},"sa":{"a":0,"k":0,"ix":5},"nm":"Transform"}],"nm":"Bubble","np":4,"cix":2,"ix":1,"mn":"ADBE Vector Group","hd":false}],"ip":0,"op":60,"st":0,"bm":0},{"ddd":0,"ind":4,"ty":4,"nm":"Top Hole","sr":1,"ks":{"o":{"a":0,"k":100,"ix":11},"r":{"a":0,"k":12,"ix":10},"p":{"a":0,"k":[805.827,323.476,0],"ix":2},"a":{"a":0,"k":[5.714,-14,0],"ix":1},"s":{"a":0,"k":[1400,1400,100],"ix":6}},"ao":0,"shapes":[{"ty":"gr","it":[{"ind":0,"ty":"sh","ix":1,"ks":{"a":0,"k":{"i":[[-0.131,-0.49],[2.927,-0.785],[0.143,0.533],[-2.906,0.779]],"o":[[0.143,0.531],[-2.926,0.785],[-0.135,-0.488],[2.945,-0.791]],"v":[[11.011,-15.4],[6.019,-12.849],[0.417,-12.562],[5.38,-15.232]],"c":true},"ix":2},"nm":"Path 1","mn":"ADBE Vector Shape - Group","hd":false},{"ty":"fl","c":{"a":0,"k":[0.901960790157,0.921568632126,0.937254905701,1],"ix":4},"o":{"a":0,"k":100,"ix":5},"r":1,"nm":"Fill 1","mn":"ADBE Vector Graphic - Fill","hd":false},{"ty":"tr","p":{"a":0,"k":[0,0],"ix":2},"a":{"a":0,"k":[0,0],"ix":1},"s":{"a":0,"k":[100,100],"ix":3},"r":{"a":0,"k":0,"ix":6},"o":{"a":0,"k":100,"ix":7},"sk":{"a":0,"k":0,"ix":4},"sa":{"a":0,"k":0,"ix":5},"nm":"Transform"}],"nm":"Top Hole","np":2,"cix":2,"ix":1,"mn":"ADBE Vector Group","hd":false}],"ip":0,"op":60,"st":0,"bm":0},{"ddd":0,"ind":5,"ty":4,"nm":"Top","sr":1,"ks":{"o":{"a":0,"k":100,"ix":11},"r":{"a":0,"k":12,"ix":10},"p":{"a":0,"k":[805.678,324.127,0],"ix":2},"a":{"a":0,"k":[5.714,-13.952,0],"ix":1},"s":{"a":0,"k":[1400,1400,100],"ix":6}},"ao":0,"shapes":[{"ty":"gr","it":[{"ind":0,"ty":"sh","ix":1,"ks":{"a":0,"k":{"i":[[-0.18,-0.677],[3.255,-0.869],[0.257,0.955],[-3.231,0.866]],"o":[[0.259,0.955],[-3.25,0.871],[-0.183,-0.678],[3.274,-0.875]],"v":[[11.594,-15.574],[6.173,-12.269],[-0.176,-12.419],[5.247,-15.728]],"c":true},"ix":2},"nm":"Path 1","mn":"ADBE Vector Shape - Group","hd":false},{"ty":"fl","c":{"a":0,"k":[0.772549033165,0.843137264252,0.909803926945,1],"ix":4},"o":{"a":0,"k":100,"ix":5},"r":1,"nm":"Fill 1","mn":"ADBE Vector Graphic - Fill","hd":false},{"ty":"tr","p":{"a":0,"k":[0,0],"ix":2},"a":{"a":0,"k":[0,0],"ix":1},"s":{"a":0,"k":[100,100],"ix":3},"r":{"a":0,"k":0,"ix":6},"o":{"a":0,"k":100,"ix":7},"sk":{"a":0,"k":0,"ix":4},"sa":{"a":0,"k":0,"ix":5},"nm":"Transform"}],"nm":"Top","np":2,"cix":2,"ix":1,"mn":"ADBE Vector Group","hd":false}],"ip":0,"op":60,"st":0,"bm":0},{"ddd":0,"ind":6,"ty":4,"nm":"Foam","td":1,"sr":1,"ks":{"o":{"a":0,"k":100,"ix":11},"r":{"a":0,"k":12,"ix":10},"p":{"a":0,"k":[813.355,408.472,0],"ix":2},"a":{"a":0,"k":[7.503,-8.173,0],"ix":1},"s":{"a":0,"k":[1400,1400,100],"ix":6}},"ao":0,"shapes":[{"ty":"gr","it":[{"ind":0,"ty":"sh","ix":1,"ks":{"a":1,"k":[{"i":{"x":0.833,"y":0.833},"o":{"x":0.167,"y":0.167},"n":"0p833_0p833_0p167_0p167","t":0,"s":[{"i":[[-0.405,-2.28],[-4.854,1.1],[0,0],[5.704,-1.077]],"o":[[5.645,-0.927],[-0.451,-1.535],[-3.86,1.149],[0,-0.001]],"v":[[-0.547,-5.382],[15.291,-8.399],[13.341,-12.261],[-1.059,-9.079]],"c":true}],"e":[{"i":[[-0.405,-2.28],[-4.559,2.943],[0,0],[6.572,0.231]],"o":[[6.023,-0.768],[-0.451,-1.535],[-3.876,1.775],[0,-0.001]],"v":[[0.983,-7.46],[14.534,-6.12],[13.546,-9.237],[0.471,-11.157]],"c":true}]},{"i":{"x":0.833,"y":0.833},"o":{"x":0.167,"y":0.167},"n":"0p833_0p833_0p167_0p167","t":8,"s":[{"i":[[-0.405,-2.28],[-4.559,2.943],[0,0],[6.572,0.231]],"o":[[6.023,-0.768],[-0.451,-1.535],[-3.876,1.775],[0,-0.001]],"v":[[0.983,-7.46],[14.534,-6.12],[13.546,-9.237],[0.471,-11.157]],"c":true}],"e":[{"i":[[-0.405,-2.28],[-4.761,1.476],[0,0],[6.572,0.231]],"o":[[7.298,-0.353],[-0.451,-1.535],[-3.876,1.775],[0,-0.001]],"v":[[-0.041,-2.711],[14.245,-9.465],[12.892,-13.482],[-0.184,-7.946]],"c":true}]},{"i":{"x":0.833,"y":0.833},"o":{"x":0.167,"y":0.167},"n":"0p833_0p833_0p167_0p167","t":15,"s":[{"i":[[-0.405,-2.28],[-4.761,1.476],[0,0],[6.572,0.231]],"o":[[7.298,-0.353],[-0.451,-1.535],[-3.876,1.775],[0,-0.001]],"v":[[-0.041,-2.711],[14.245,-9.465],[12.892,-13.482],[-0.184,-7.946]],"c":true}],"e":[{"i":[[-0.405,-2.28],[-4.559,2.943],[0,0],[6.572,0.231]],"o":[[6.023,-0.768],[-0.451,-1.535],[-3.876,1.775],[0,-0.001]],"v":[[0.983,-7.46],[14.534,-6.12],[13.546,-9.237],[0.471,-11.157]],"c":true}]},{"i":{"x":0.833,"y":0.833},"o":{"x":0.167,"y":0.167},"n":"0p833_0p833_0p167_0p167","t":22,"s":[{"i":[[-0.405,-2.28],[-4.559,2.943],[0,0],[6.572,0.231]],"o":[[6.023,-0.768],[-0.451,-1.535],[-3.876,1.775],[0,-0.001]],"v":[[0.983,-7.46],[14.534,-6.12],[13.546,-9.237],[0.471,-11.157]],"c":true}],"e":[{"i":[[-0.405,-2.28],[-4.761,1.476],[0,0],[6.572,0.231]],"o":[[7.298,-0.353],[-0.451,-1.535],[-3.876,1.775],[0,-0.001]],"v":[[-0.231,-3.734],[14.979,-8.633],[13.626,-12.651],[-0.374,-8.968]],"c":true}]},{"i":{"x":0.833,"y":0.833},"o":{"x":0.167,"y":0.167},"n":"0p833_0p833_0p167_0p167","t":28,"s":[{"i":[[-0.405,-2.28],[-4.761,1.476],[0,0],[6.572,0.231]],"o":[[7.298,-0.353],[-0.451,-1.535],[-3.876,1.775],[0,-0.001]],"v":[[-0.231,-3.734],[14.979,-8.633],[13.626,-12.651],[-0.374,-8.968]],"c":true}],"e":[{"i":[[-0.405,-2.28],[-4.559,2.943],[0,0],[6.572,0.231]],"o":[[6.023,-0.768],[-0.451,-1.535],[-3.876,1.775],[0,-0.001]],"v":[[-0.916,-5.742],[15.291,-8.399],[14.303,-11.516],[-1.428,-9.439]],"c":true}]},{"i":{"x":0.833,"y":0.833},"o":{"x":0.167,"y":0.167},"n":"0p833_0p833_0p167_0p167","t":36,"s":[{"i":[[-0.405,-2.28],[-4.559,2.943],[0,0],[6.572,0.231]],"o":[[6.023,-0.768],[-0.451,-1.535],[-3.876,1.775],[0,-0.001]],"v":[[-0.916,-5.742],[15.291,-8.399],[14.303,-11.516],[-1.428,-9.439]],"c":true}],"e":[{"i":[[-0.405,-2.28],[-4.854,1.1],[0,0],[5.704,-1.077]],"o":[[5.645,-0.927],[-0.451,-1.535],[-3.86,1.149],[0,-0.001]],"v":[[-0.547,-5.382],[15.291,-8.399],[13.341,-12.261],[-1.059,-9.079]],"c":true}]},{"t":42}],"ix":2},"nm":"Path 1","mn":"ADBE Vector Shape - Group","hd":false},{"ty":"fl","c":{"a":0,"k":[1,0.909803926945,0.733333349228,1],"ix":4},"o":{"a":0,"k":100,"ix":5},"r":1,"nm":"Fill 1","mn":"ADBE Vector Graphic - Fill","hd":false},{"ty":"tr","p":{"a":0,"k":[0,0],"ix":2},"a":{"a":0,"k":[0,0],"ix":1},"s":{"a":0,"k":[100,100],"ix":3},"r":{"a":0,"k":0,"ix":6},"o":{"a":0,"k":100,"ix":7},"sk":{"a":0,"k":0,"ix":4},"sa":{"a":0,"k":0,"ix":5},"nm":"Transform"}],"nm":"Foam","np":2,"cix":2,"ix":1,"mn":"ADBE Vector Group","hd":false}],"ip":0,"op":60,"st":0,"bm":0},{"ddd":0,"ind":7,"ty":4,"nm":"Shape Layer 1","tt":1,"sr":1,"ks":{"o":{"a":0,"k":100,"ix":11},"r":{"a":0,"k":0,"ix":10},"p":{"a":0,"k":[512,512,0],"ix":2},"a":{"a":0,"k":[0,0,0],"ix":1},"s":{"a":0,"k":[100,100,100],"ix":6}},"ao":0,"shapes":[{"ty":"gr","it":[{"ind":0,"ty":"sh","ix":1,"ks":{"a":0,"k":{"i":[[-16.568,-48.612],[0,0],[5.341,60.848],[-3,15]],"o":[[19.086,56],[0,0],[-5,-56.961],[10.072,-50.36]],"v":[[95.457,-82.48],[118.457,100.481],[-64.457,89.48],[-60.207,-74.48]],"c":true},"ix":2},"nm":"Path 1","mn":"ADBE Vector Shape - Group","hd":false},{"ty":"fl","c":{"a":0,"k":[1,0.909803926945,0.733333349228,1],"ix":4},"o":{"a":0,"k":100,"ix":5},"r":1,"nm":"Fill 2","mn":"ADBE Vector Graphic - Fill","hd":false},{"ty":"tr","p":{"a":0,"k":[276.457,-101.52],"ix":2},"a":{"a":0,"k":[0,0],"ix":1},"s":{"a":0,"k":[100,100],"ix":3},"r":{"a":0,"k":0,"ix":6},"o":{"a":0,"k":100,"ix":7},"sk":{"a":0,"k":0,"ix":4},"sa":{"a":0,"k":0,"ix":5},"nm":"Transform"}],"nm":"Rectangle 1","np":2,"cix":2,"ix":1,"mn":"ADBE Vector Group","hd":false}],"ip":0,"op":60,"st":0,"bm":0},{"ddd":0,"ind":8,"ty":4,"nm":"Glass Shadow","sr":1,"ks":{"o":{"a":0,"k":100,"ix":11},"r":{"a":0,"k":12,"ix":10},"p":{"a":0,"k":[828.925,696.34,0],"ix":2},"a":{"a":0,"k":[12.865,11.708,0],"ix":1},"s":{"a":0,"k":[1400,1400,100],"ix":6}},"ao":0,"shapes":[{"ty":"gr","it":[{"ind":0,"ty":"sh","ix":1,"ks":{"a":0,"k":{"i":[[0.111,0.416],[1.746,-0.623],[-0.094,-0.356],[-0.683,0.188]],"o":[[-0.069,-0.264],[-1.17,0.418],[0.039,0.152],[0.72,-0.191]],"v":[[15.132,10.498],[12.37,12.029],[10.602,12.457],[12.891,12.914]],"c":true},"ix":2},"nm":"Path 1","mn":"ADBE Vector Shape - Group","hd":false},{"ty":"fl","c":{"a":0,"k":[0.600000023842,0.658823549747,0.68235296011,1],"ix":4},"o":{"a":0,"k":100,"ix":5},"r":1,"nm":"Fill 1","mn":"ADBE Vector Graphic - Fill","hd":false},{"ty":"tr","p":{"a":0,"k":[0,0],"ix":2},"a":{"a":0,"k":[0,0],"ix":1},"s":{"a":0,"k":[100,100],"ix":3},"r":{"a":0,"k":0,"ix":6},"o":{"a":0,"k":100,"ix":7},"sk":{"a":0,"k":0,"ix":4},"sa":{"a":0,"k":0,"ix":5},"nm":"Transform"}],"nm":"Glass Shadow","np":2,"cix":2,"ix":1,"mn":"ADBE Vector Group","hd":false}],"ip":0,"op":60,"st":0,"bm":0},{"ddd":0,"ind":9,"ty":4,"nm":"Liquid","sr":1,"ks":{"o":{"a":0,"k":100,"ix":11},"r":{"a":0,"k":12,"ix":10},"p":{"a":0,"k":[799.037,533.009,0],"ix":2},"a":{"a":0,"k":[8.352,0.74,0],"ix":1},"s":{"a":0,"k":[1400,1400,100],"ix":6}},"ao":0,"shapes":[{"ty":"gr","it":[{"ind":0,"ty":"sh","ix":1,"ks":{"a":1,"k":[{"i":{"x":0.833,"y":0.833},"o":{"x":0.167,"y":0.167},"n":"0p833_0p833_0p167_0p167","t":12,"s":[{"i":[[1.242,10.254],[-10.256,-0.443],[4.963,-1.332]],"o":[[0,0],[2.708,8.539],[-5.83,1.559]],"v":[[0.761,-9.479],[13.927,-8.162],[12.335,10.746]],"c":true}],"e":[{"i":[[1.242,10.254],[-9.281,1.846],[4.963,-1.332]],"o":[[0,0],[3.088,8.915],[-5.83,1.559]],"v":[[1.054,-7.748],[13.532,-9.418],[12.335,10.746]],"c":true}]},{"i":{"x":0.833,"y":0.833},"o":{"x":0.167,"y":0.167},"n":"0p833_0p833_0p167_0p167","t":15,"s":[{"i":[[1.242,10.254],[-9.281,1.846],[4.963,-1.332]],"o":[[0,0],[3.088,8.915],[-5.83,1.559]],"v":[[1.054,-7.748],[13.532,-9.418],[12.335,10.746]],"c":true}],"e":[{"i":[[1.242,10.254],[-10.256,-0.443],[4.963,-1.332]],"o":[[0,0],[2.708,8.539],[-5.83,1.559]],"v":[[0.761,-9.479],[13.927,-8.162],[12.335,10.746]],"c":true}]},{"i":{"x":0.833,"y":0.833},"o":{"x":0.167,"y":0.167},"n":"0p833_0p833_0p167_0p167","t":23,"s":[{"i":[[1.242,10.254],[-10.256,-0.443],[4.963,-1.332]],"o":[[0,0],[2.708,8.539],[-5.83,1.559]],"v":[[0.761,-9.479],[13.927,-8.162],[12.335,10.746]],"c":true}],"e":[{"i":[[1.242,10.254],[-10.256,-0.443],[4.963,-1.332]],"o":[[0,0],[2.708,8.539],[-5.83,1.559]],"v":[[0.859,-8.854],[13.927,-8.162],[12.335,10.746]],"c":true}]},{"i":{"x":0.833,"y":0.833},"o":{"x":0.167,"y":0.167},"n":"0p833_0p833_0p167_0p167","t":29,"s":[{"i":[[1.242,10.254],[-10.256,-0.443],[4.963,-1.332]],"o":[[0,0],[2.708,8.539],[-5.83,1.559]],"v":[[0.859,-8.854],[13.927,-8.162],[12.335,10.746]],"c":true}],"e":[{"i":[[1.242,10.254],[-10.256,-0.443],[4.963,-1.332]],"o":[[0,0],[2.708,8.539],[-5.83,1.559]],"v":[[0.761,-9.479],[13.927,-8.162],[12.335,10.746]],"c":true}]},{"t":33}],"ix":2},"nm":"Path 1","mn":"ADBE Vector Shape - Group","hd":false},{"ty":"gf","o":{"a":0,"k":100,"ix":10},"r":1,"g":{"p":9,"k":{"a":0,"k":[0,1,0.784,0.278,0.028,1,0.79,0.288,0.056,1,0.796,0.298,0.227,1,0.827,0.341,0.397,1,0.859,0.384,0.558,1,0.878,0.412,0.719,1,0.898,0.439,0.86,1,0.904,0.449,1,1,0.91,0.459],"ix":9}},"s":{"a":0,"k":[12.414,10.805],"ix":5},"e":{"a":0,"k":[5.48,-11.736],"ix":6},"t":1,"nm":"liquidgradientzazea","mn":"ADBE Vector Graphic - G-Fill","hd":false},{"ty":"tr","p":{"a":0,"k":[0,0],"ix":2},"a":{"a":0,"k":[0,0],"ix":1},"s":{"a":0,"k":[100,100],"ix":3},"r":{"a":0,"k":0,"ix":6},"o":{"a":0,"k":100,"ix":7},"sk":{"a":0,"k":0,"ix":4},"sa":{"a":0,"k":0,"ix":5},"nm":"Transform"}],"nm":"Liquid","np":2,"cix":2,"ix":1,"mn":"ADBE Vector Group","hd":false}],"ip":0,"op":60,"st":0,"bm":0},{"ddd":0,"ind":10,"ty":4,"nm":"Glass top bg","sr":1,"ks":{"o":{"a":0,"k":100,"ix":11},"r":{"a":0,"k":12,"ix":10},"p":{"a":0,"k":[811.038,466.892,0],"ix":2},"a":{"a":0,"k":[8.208,-4.057,0],"ix":1},"s":{"a":0,"k":[1400,1400,100],"ix":6}},"ao":0,"shapes":[{"ty":"gr","it":[{"ind":0,"ty":"sh","ix":1,"ks":{"a":0,"k":{"i":[[0.262,3.123],[-1.139,0.318],[-1.273,-0.836],[-1.244,-11.217],[0,0]],"o":[[0.682,-1.35],[1.141,-0.291],[0.214,0.16],[0,0],[-4.744,-6.94]],"v":[[0.423,-12.531],[5.353,-15.32],[11.025,-15.365],[15.994,2.342],[6.41,7.68]],"c":true},"ix":2},"nm":"Path 1","mn":"ADBE Vector Shape - Group","hd":false},{"ty":"fl","c":{"a":0,"k":[0.901960790157,0.921568632126,0.937254905701,1],"ix":4},"o":{"a":0,"k":100,"ix":5},"r":1,"nm":"Fill 1","mn":"ADBE Vector Graphic - Fill","hd":false},{"ty":"tr","p":{"a":0,"k":[0,0],"ix":2},"a":{"a":0,"k":[0,0],"ix":1},"s":{"a":0,"k":[100,100],"ix":3},"r":{"a":0,"k":0,"ix":6},"o":{"a":0,"k":100,"ix":7},"sk":{"a":0,"k":0,"ix":4},"sa":{"a":0,"k":0,"ix":5},"nm":"Transform"}],"nm":"Glass top bg","np":2,"cix":2,"ix":1,"mn":"ADBE Vector Group","hd":false}],"ip":0,"op":60,"st":0,"bm":0},{"ddd":0,"ind":11,"ty":4,"nm":"Glass top","sr":1,"ks":{"o":{"a":0,"k":100,"ix":11},"r":{"a":0,"k":12,"ix":10},"p":{"a":0,"k":[805.817,507.092,0],"ix":2},"a":{"a":0,"k":[8.44,-1.171,0],"ix":1},"s":{"a":0,"k":[1400,1400,100],"ix":6}},"ao":0,"shapes":[{"ty":"gr","it":[{"ind":0,"ty":"sh","ix":1,"ks":{"a":0,"k":{"i":[[0.688,0.437],[0.959,-1.853],[-11.081,-0.289]],"o":[[-1.757,-1.121],[-0.381,0.721],[9.45,-5.791]],"v":[[11.469,-15.759],[-0.159,-12.644],[13.135,13.705]],"c":true},"ix":2},"nm":"Path 1","mn":"ADBE Vector Shape - Group","hd":false},{"ty":"fl","c":{"a":0,"k":[0.772549033165,0.843137264252,0.909803926945,1],"ix":4},"o":{"a":0,"k":100,"ix":5},"r":1,"nm":"Fill 1","mn":"ADBE Vector Graphic - Fill","hd":false},{"ty":"tr","p":{"a":0,"k":[0,0],"ix":2},"a":{"a":0,"k":[0,0],"ix":1},"s":{"a":0,"k":[100,100],"ix":3},"r":{"a":0,"k":0,"ix":6},"o":{"a":0,"k":100,"ix":7},"sk":{"a":0,"k":0,"ix":4},"sa":{"a":0,"k":0,"ix":5},"nm":"Transform"}],"nm":"Glass top","np":2,"cix":2,"ix":1,"mn":"ADBE Vector Group","hd":false}],"ip":0,"op":60,"st":0,"bm":0},{"ddd":0,"ind":12,"ty":4,"nm":"Bot Highlight","sr":1,"ks":{"o":{"a":0,"k":100,"ix":11},"r":{"a":0,"k":12,"ix":10},"p":{"a":0,"k":[806.361,931.192,0],"ix":2},"a":{"a":0,"k":[14.777,28.452,0],"ix":1},"s":{"a":0,"k":[1400,1400,100],"ix":6}},"ao":0,"shapes":[{"ty":"gr","it":[{"ind":0,"ty":"sh","ix":1,"ks":{"a":0,"k":{"i":[[-3.726,0.996],[-2.173,1.776],[-0.129,-0.473]],"o":[[4.516,-1.209],[1.771,-1.453],[0.14,0.531]],"v":[[17.417,28.6],[13.146,27.967],[11.037,29.098]],"c":true},"ix":2},"nm":"Path 1","mn":"ADBE Vector Shape - Group","hd":false},{"ty":"fl","c":{"a":0,"k":[0.901960790157,0.921568632126,0.937254905701,1],"ix":4},"o":{"a":0,"k":100,"ix":5},"r":1,"nm":"Fill 1","mn":"ADBE Vector Graphic - Fill","hd":false},{"ty":"tr","p":{"a":0,"k":[0,0],"ix":2},"a":{"a":0,"k":[0,0],"ix":1},"s":{"a":0,"k":[100,100],"ix":3},"r":{"a":0,"k":0,"ix":6},"o":{"a":0,"k":100,"ix":7},"sk":{"a":0,"k":0,"ix":4},"sa":{"a":0,"k":0,"ix":5},"nm":"Transform"}],"nm":"Bot Highlight","np":2,"cix":2,"ix":1,"mn":"ADBE Vector Group","hd":false}],"ip":0,"op":60,"st":0,"bm":0},{"ddd":0,"ind":13,"ty":4,"nm":"Bot","sr":1,"ks":{"o":{"a":0,"k":100,"ix":11},"r":{"a":0,"k":12,"ix":10},"p":{"a":0,"k":[856.592,835.558,0],"ix":2},"a":{"a":0,"k":[16.866,21.024,0],"ix":1},"s":{"a":0,"k":[1400,1400,100],"ix":6}},"ao":0,"shapes":[{"ty":"gr","it":[{"ind":0,"ty":"sh","ix":1,"ks":{"a":0,"k":{"i":[[-2.403,0.875],[1.133,4.231],[0,0],[0,0],[-1.801,-6.724],[-1.296,-0.891],[-0.175,-0.652],[3.661,-0.98],[0.226,0.852]],"o":[[0.671,-1.422],[-1.801,-6.723],[0,0],[0,0],[1.132,4.229],[2.52,-0.432],[0.227,0.855],[-3.659,0.986],[-0.175,-0.659]],"v":[[14.388,26.752],[14.005,20.037],[10.749,13.17],[14.926,12.049],[15.542,19.627],[18.565,25.627],[23.487,25.869],[17.277,29.187],[10.243,29.421]],"c":true},"ix":2},"nm":"Path 1","mn":"ADBE Vector Shape - Group","hd":false},{"ty":"fl","c":{"a":0,"k":[0.772549033165,0.843137264252,0.909803926945,1],"ix":4},"o":{"a":0,"k":100,"ix":5},"r":1,"nm":"Fill 1","mn":"ADBE Vector Graphic - Fill","hd":false},{"ty":"tr","p":{"a":0,"k":[0,0],"ix":2},"a":{"a":0,"k":[0,0],"ix":1},"s":{"a":0,"k":[100,100],"ix":3},"r":{"a":0,"k":0,"ix":6},"o":{"a":0,"k":100,"ix":7},"sk":{"a":0,"k":0,"ix":4},"sa":{"a":0,"k":0,"ix":5},"nm":"Transform"}],"nm":"Bot","np":2,"cix":2,"ix":1,"mn":"ADBE Vector Group","hd":false}],"ip":0,"op":60,"st":0,"bm":0}]},{"id":"comp_1","layers":[{"ddd":0,"ind":1,"ty":4,"nm":"Glass Highlight","sr":1,"ks":{"o":{"a":0,"k":70,"ix":11},"r":{"a":0,"k":12,"ix":10},"p":{"a":0,"k":[764.097,500.69,0],"ix":2},"a":{"a":0,"k":[5.431,-0.999,0],"ix":1},"s":{"a":0,"k":[1400,1400,100],"ix":6}},"ao":0,"shapes":[{"ty":"gr","it":[{"ind":0,"ty":"sh","ix":1,"ks":{"a":0,"k":{"i":[[1.488,0.35],[-5.67,-5.719],[0.968,1.691],[0,0]],"o":[[0,0],[0.894,0.904],[-5.236,-9.126],[0,0]],"v":[[0.876,-11.146],[8.062,8.74],[9.697,7.867],[3.895,-11.308]],"c":true},"ix":2},"nm":"Path 1","mn":"ADBE Vector Shape - Group","hd":false},{"ty":"gf","o":{"a":0,"k":100,"ix":10},"r":1,"g":{"p":5,"k":{"a":0,"k":[0,1,1,1,0.057,1,1,1,0.114,1,1,1,0.557,1,1,1,1,1,1,1,0,0,0.057,0.057,0.114,0.114,0.557,0.557,1,1],"ix":9}},"s":{"a":0,"k":[8.163,10.024],"ix":5},"e":{"a":0,"k":[2.196,-11.453],"ix":6},"t":1,"nm":"highlight gradientazaezaezaezaeaze","mn":"ADBE Vector Graphic - G-Fill","hd":false},{"ty":"tr","p":{"a":0,"k":[0,0],"ix":2},"a":{"a":0,"k":[0,0],"ix":1},"s":{"a":0,"k":[100,100],"ix":3},"r":{"a":0,"k":0,"ix":6},"o":{"a":0,"k":100,"ix":7},"sk":{"a":0,"k":0,"ix":4},"sa":{"a":0,"k":0,"ix":5},"nm":"Transform"}],"nm":"Glass Highlight","np":2,"cix":2,"ix":1,"mn":"ADBE Vector Group","hd":false}],"ip":0,"op":60,"st":0,"bm":0},{"ddd":0,"ind":2,"ty":4,"nm":"BotShadow","sr":1,"ks":{"o":{"a":0,"k":100,"ix":11},"r":{"a":0,"k":12,"ix":10},"p":{"a":0,"k":[859.919,903.952,0],"ix":2},"a":{"a":0,"k":[18.114,25.753,0],"ix":1},"s":{"a":0,"k":[1400,1400,100],"ix":6}},"ao":0,"shapes":[{"ty":"gr","it":[{"ind":0,"ty":"sh","ix":1,"ks":{"a":0,"k":{"i":[[-0.673,-0.602],[0.154,-0.064]],"o":[[1.473,1.313],[-1.526,0.627]],"v":[[16.983,24.795],[19.392,26.705]],"c":true},"ix":2},"nm":"Path 1","mn":"ADBE Vector Shape - Group","hd":false},{"ty":"fl","c":{"a":0,"k":[0.588235318661,0.666666686535,0.690196096897,1],"ix":4},"o":{"a":0,"k":100,"ix":5},"r":1,"nm":"Fill 1","mn":"ADBE Vector Graphic - Fill","hd":false},{"ty":"tr","p":{"a":0,"k":[0,0],"ix":2},"a":{"a":0,"k":[0,0],"ix":1},"s":{"a":0,"k":[100,100],"ix":3},"r":{"a":0,"k":0,"ix":6},"o":{"a":0,"k":100,"ix":7},"sk":{"a":0,"k":0,"ix":4},"sa":{"a":0,"k":0,"ix":5},"nm":"Transform"}],"nm":"BotShadow","np":2,"cix":2,"ix":1,"mn":"ADBE Vector Group","hd":false}],"ip":0,"op":60,"st":0,"bm":0},{"ddd":0,"ind":3,"ty":4,"nm":"Bubble","sr":1,"ks":{"o":{"a":0,"k":100,"ix":11},"r":{"a":0,"k":12,"ix":10},"p":{"a":0,"k":[822.726,550.903,0],"ix":2},"a":{"a":0,"k":[10.272,1.639,0],"ix":1},"s":{"a":0,"k":[1400,1400,100],"ix":6}},"ao":0,"shapes":[{"ty":"gr","it":[{"ty":"gr","it":[{"ind":0,"ty":"sh","ix":1,"ks":{"a":0,"k":{"i":[[-0.17,-0.64],[0.171,0.642]],"o":[[0.174,0.645],[-0.173,-0.646]],"v":[[6.53,-2.326],[5.565,-2.064]],"c":true},"ix":2},"nm":"Path 1","mn":"ADBE Vector Shape - Group","hd":false},{"ty":"fl","c":{"a":0,"k":[1,0.909803926945,0.733333349228,1],"ix":4},"o":{"a":0,"k":100,"ix":5},"r":1,"nm":"Fill 1","mn":"ADBE Vector Graphic - Fill","hd":false},{"ty":"tr","p":{"a":1,"k":[{"i":{"x":0.667,"y":1},"o":{"x":0.333,"y":0},"n":"0p667_1_0p333_0","t":0,"s":[7.534,6.566],"e":[5.206,-1.669],"to":[-0.38799199461937,-1.37258994579315],"ti":[0,0]},{"i":{"x":0.667,"y":1},"o":{"x":0.333,"y":0},"n":"0p667_1_0p333_0","t":13,"s":[5.206,-1.669],"e":[7.534,6.566],"to":[0,0],"ti":[0,0]},{"i":{"x":0.667,"y":1},"o":{"x":0.333,"y":0},"n":"0p667_1_0p333_0","t":27,"s":[7.534,6.566],"e":[5.206,-1.669],"to":[0,0],"ti":[0.38799199461937,1.37258994579315]},{"t":40}],"ix":2},"a":{"a":0,"k":[6.048,-2.195],"ix":1},"s":{"a":1,"k":[{"i":{"x":[0.667,0.667],"y":[1,1]},"o":{"x":[0.333,0.333],"y":[0,0]},"n":["0p667_1_0p333_0","0p667_1_0p333_0"],"t":0,"s":[0,0],"e":[100,100]},{"i":{"x":[0.667,0.667],"y":[1,1]},"o":{"x":[0.333,0.333],"y":[0,0]},"n":["0p667_1_0p333_0","0p667_1_0p333_0"],"t":4,"s":[100,100],"e":[0,0]},{"i":{"x":[0.667,0.667],"y":[1,1]},"o":{"x":[0.333,0.333],"y":[0,0]},"n":["0p667_1_0p333_0","0p667_1_0p333_0"],"t":27,"s":[0,0],"e":[100,100]},{"t":31}],"ix":3},"r":{"a":0,"k":0,"ix":6},"o":{"a":1,"k":[{"i":{"x":[0.833],"y":[1]},"o":{"x":[0.333],"y":[0]},"n":["0p833_1_0p333_0"],"t":0,"s":[100],"e":[100]},{"i":{"x":[0.833],"y":[1]},"o":{"x":[0.167],"y":[0]},"n":["0p833_1_0p167_0"],"t":9,"s":[100],"e":[0]},{"i":{"x":[0.667],"y":[1]},"o":{"x":[0.167],"y":[0]},"n":["0p667_1_0p167_0"],"t":13,"s":[0],"e":[100]},{"i":{"x":[0.833],"y":[1]},"o":{"x":[0.333],"y":[0]},"n":["0p833_1_0p333_0"],"t":27,"s":[100],"e":[100]},{"i":{"x":[0.833],"y":[1]},"o":{"x":[0.167],"y":[0]},"n":["0p833_1_0p167_0"],"t":36,"s":[100],"e":[0]},{"t":40}],"ix":7},"sk":{"a":0,"k":0,"ix":4},"sa":{"a":0,"k":0,"ix":5},"nm":"Transform"}],"nm":"Group 1","np":2,"cix":2,"ix":1,"mn":"ADBE Vector Group","hd":false},{"ty":"gr","it":[{"ind":0,"ty":"sh","ix":1,"ks":{"a":0,"k":{"i":[[-0.346,-1.289],[0.344,1.288]],"o":[[0.345,1.285],[-0.344,-1.284]],"v":[[9.676,-0.253],[7.745,0.263]],"c":true},"ix":2},"nm":"Path 2","mn":"ADBE Vector Shape - Group","hd":false},{"ty":"fl","c":{"a":0,"k":[1,0.909803926945,0.733333349228,1],"ix":4},"o":{"a":0,"k":100,"ix":5},"r":1,"nm":"Fill 2","mn":"ADBE Vector Graphic - Fill","hd":false},{"ty":"tr","p":{"a":1,"k":[{"i":{"x":0.667,"y":1},"o":{"x":0.333,"y":0},"n":"0p667_1_0p333_0","t":5,"s":[11.48,8.192],"e":[8.561,-2.668],"to":[-0.48660373687744,-1.8100129365921],"ti":[0,0]},{"i":{"x":0.833,"y":1},"o":{"x":0.167,"y":0},"n":"0p833_1_0p167_0","t":18,"s":[8.561,-2.668],"e":[11.48,8.192],"to":[0,0],"ti":[0,0]},{"i":{"x":0.667,"y":1},"o":{"x":0.333,"y":0},"n":"0p667_1_0p333_0","t":38,"s":[11.48,8.192],"e":[8.561,-2.668],"to":[0,0],"ti":[0.48660373687744,1.8100129365921]},{"t":51}],"ix":2},"a":{"a":0,"k":[8.711,0.005],"ix":1},"s":{"a":1,"k":[{"i":{"x":[0.667,0.667],"y":[1,1]},"o":{"x":[0.333,0.333],"y":[0,0]},"n":["0p667_1_0p333_0","0p667_1_0p333_0"],"t":5,"s":[0,0],"e":[100,100]},{"i":{"x":[0.833,0.833],"y":[1,1]},"o":{"x":[0.167,0.167],"y":[0,0]},"n":["0p833_1_0p167_0","0p833_1_0p167_0"],"t":9,"s":[100,100],"e":[0,0]},{"i":{"x":[0.667,0.667],"y":[1,1]},"o":{"x":[0.333,0.333],"y":[0,0]},"n":["0p667_1_0p333_0","0p667_1_0p333_0"],"t":38,"s":[0,0],"e":[100,100]},{"t":42}],"ix":3},"r":{"a":0,"k":0,"ix":6},"o":{"a":1,"k":[{"i":{"x":[0.667],"y":[1]},"o":{"x":[0.333],"y":[0]},"n":["0p667_1_0p333_0"],"t":5,"s":[100],"e":[100]},{"i":{"x":[0.667],"y":[1]},"o":{"x":[0.333],"y":[0]},"n":["0p667_1_0p333_0"],"t":13,"s":[100],"e":[0]},{"i":{"x":[0.833],"y":[1]},"o":{"x":[0.167],"y":[0]},"n":["0p833_1_0p167_0"],"t":18,"s":[0],"e":[100]},{"i":{"x":[0.667],"y":[1]},"o":{"x":[0.333],"y":[0]},"n":["0p667_1_0p333_0"],"t":38,"s":[100],"e":[100]},{"i":{"x":[0.667],"y":[1]},"o":{"x":[0.333],"y":[0]},"n":["0p667_1_0p333_0"],"t":46,"s":[100],"e":[0]},{"t":51}],"ix":7},"sk":{"a":0,"k":0,"ix":4},"sa":{"a":0,"k":0,"ix":5},"nm":"Transform"}],"nm":"Group 2","np":2,"cix":2,"ix":2,"mn":"ADBE Vector Group","hd":false},{"ty":"gr","it":[{"ind":0,"ty":"sh","ix":1,"ks":{"a":0,"k":{"i":[[-0.255,-0.958],[0.261,0.972]],"o":[[0.262,0.971],[-0.258,-0.963]],"v":[[7.888,1.773],[6.441,2.164]],"c":true},"ix":2},"nm":"Path 3","mn":"ADBE Vector Shape - Group","hd":false},{"ty":"fl","c":{"a":0,"k":[1,0.909803926945,0.733333349228,1],"ix":4},"o":{"a":0,"k":100,"ix":5},"r":1,"nm":"Fill 3","mn":"ADBE Vector Graphic - Fill","hd":false},{"ty":"tr","p":{"a":1,"k":[{"i":{"x":0.667,"y":1},"o":{"x":0.333,"y":0},"n":"0p667_1_0p333_0","t":10,"s":[9.932,8.303],"e":[5.822,-2.61],"to":[-0.68493926525116,-1.81886923313141],"ti":[0,0]},{"i":{"x":0.833,"y":1},"o":{"x":0.167,"y":0},"n":"0p833_1_0p167_0","t":28,"s":[5.822,-2.61],"e":[9.932,8.303],"to":[0,0],"ti":[0,0]},{"i":{"x":0.667,"y":1},"o":{"x":0.333,"y":0},"n":"0p667_1_0p333_0","t":42,"s":[9.932,8.303],"e":[5.822,-2.61],"to":[0,0],"ti":[0.68493926525116,1.81886923313141]},{"t":60}],"ix":2},"a":{"a":0,"k":[7.165,1.973],"ix":1},"s":{"a":1,"k":[{"i":{"x":[0.667,0.667],"y":[1,1]},"o":{"x":[0.333,0.333],"y":[0,0]},"n":["0p667_1_0p333_0","0p667_1_0p333_0"],"t":10,"s":[0,0],"e":[100,100]},{"i":{"x":[0.833,0.833],"y":[1,1]},"o":{"x":[0.167,0.167],"y":[0,0]},"n":["0p833_1_0p167_0","0p833_1_0p167_0"],"t":15,"s":[100,100],"e":[0,0]},{"i":{"x":[0.667,0.667],"y":[1,1]},"o":{"x":[0.333,0.333],"y":[0,0]},"n":["0p667_1_0p333_0","0p667_1_0p333_0"],"t":42,"s":[0,0],"e":[100,100]},{"t":47}],"ix":3},"r":{"a":0,"k":0,"ix":6},"o":{"a":1,"k":[{"i":{"x":[0.667],"y":[1]},"o":{"x":[0.333],"y":[0]},"n":["0p667_1_0p333_0"],"t":10,"s":[100],"e":[100]},{"i":{"x":[0.667],"y":[1]},"o":{"x":[0.333],"y":[0]},"n":["0p667_1_0p333_0"],"t":23,"s":[100],"e":[0]},{"i":{"x":[0.833],"y":[1]},"o":{"x":[0.167],"y":[0]},"n":["0p833_1_0p167_0"],"t":28,"s":[0],"e":[100]},{"i":{"x":[0.667],"y":[1]},"o":{"x":[0.333],"y":[0]},"n":["0p667_1_0p333_0"],"t":42,"s":[100],"e":[100]},{"i":{"x":[0.667],"y":[1]},"o":{"x":[0.333],"y":[0]},"n":["0p667_1_0p333_0"],"t":55,"s":[100],"e":[0]},{"t":60}],"ix":7},"sk":{"a":0,"k":0,"ix":4},"sa":{"a":0,"k":0,"ix":5},"nm":"Transform"}],"nm":"Group 3","np":2,"cix":2,"ix":3,"mn":"ADBE Vector Group","hd":false},{"ty":"gr","it":[{"ind":0,"ty":"sh","ix":1,"ks":{"a":0,"k":{"i":[[-0.433,-1.601],[0.434,1.614]],"o":[[0.431,1.617],[-0.427,-1.605]],"v":[[10.719,5.078],[8.3,5.726]],"c":true},"ix":2},"nm":"Path 4","mn":"ADBE Vector Shape - Group","hd":false},{"ty":"fl","c":{"a":0,"k":[1,0.909803926945,0.733333349228,1],"ix":4},"o":{"a":0,"k":100,"ix":5},"r":1,"nm":"Fill 4","mn":"ADBE Vector Graphic - Fill","hd":false},{"ty":"tr","p":{"a":1,"k":[{"i":{"x":0.667,"y":1},"o":{"x":0.333,"y":0},"n":"0p667_1_0p333_0","t":19,"s":[10.739,8.574],"e":[8.188,-3.304],"to":[-0.42517173290253,-1.97954058647156],"ti":[0.42517173290253,1.97954058647156]},{"t":43}],"ix":2},"a":{"a":0,"k":[9.51,5.407],"ix":1},"s":{"a":1,"k":[{"i":{"x":[0.667,0.667],"y":[1,1]},"o":{"x":[0.333,0.333],"y":[0,0]},"n":["0p667_1_0p333_0","0p667_1_0p333_0"],"t":19,"s":[0,0],"e":[100,100]},{"t":27}],"ix":3},"r":{"a":0,"k":0,"ix":6},"o":{"a":1,"k":[{"i":{"x":[0.667],"y":[1]},"o":{"x":[0.333],"y":[0]},"n":["0p667_1_0p333_0"],"t":19,"s":[100],"e":[100]},{"i":{"x":[0.667],"y":[1]},"o":{"x":[0.333],"y":[0]},"n":["0p667_1_0p333_0"],"t":37,"s":[100],"e":[0]},{"t":43}],"ix":7},"sk":{"a":0,"k":0,"ix":4},"sa":{"a":0,"k":0,"ix":5},"nm":"Transform"}],"nm":"Group 4","np":2,"cix":2,"ix":4,"mn":"ADBE Vector Group","hd":false},{"ty":"tr","p":{"a":0,"k":[0,0],"ix":2},"a":{"a":0,"k":[0,0],"ix":1},"s":{"a":0,"k":[100,100],"ix":3},"r":{"a":0,"k":0,"ix":6},"o":{"a":0,"k":100,"ix":7},"sk":{"a":0,"k":0,"ix":4},"sa":{"a":0,"k":0,"ix":5},"nm":"Transform"}],"nm":"Bubble","np":4,"cix":2,"ix":1,"mn":"ADBE Vector Group","hd":false}],"ip":0,"op":60,"st":0,"bm":0},{"ddd":0,"ind":4,"ty":4,"nm":"Top Hole","sr":1,"ks":{"o":{"a":0,"k":100,"ix":11},"r":{"a":0,"k":12,"ix":10},"p":{"a":0,"k":[805.827,323.476,0],"ix":2},"a":{"a":0,"k":[5.714,-14,0],"ix":1},"s":{"a":0,"k":[1400,1400,100],"ix":6}},"ao":0,"shapes":[{"ty":"gr","it":[{"ind":0,"ty":"sh","ix":1,"ks":{"a":0,"k":{"i":[[-0.131,-0.49],[2.927,-0.785],[0.143,0.533],[-2.906,0.779]],"o":[[0.143,0.531],[-2.926,0.785],[-0.135,-0.488],[2.945,-0.791]],"v":[[11.011,-15.4],[6.019,-12.849],[0.417,-12.562],[5.38,-15.232]],"c":true},"ix":2},"nm":"Path 1","mn":"ADBE Vector Shape - Group","hd":false},{"ty":"fl","c":{"a":0,"k":[0.901960790157,0.921568632126,0.937254905701,1],"ix":4},"o":{"a":0,"k":100,"ix":5},"r":1,"nm":"Fill 1","mn":"ADBE Vector Graphic - Fill","hd":false},{"ty":"tr","p":{"a":0,"k":[0,0],"ix":2},"a":{"a":0,"k":[0,0],"ix":1},"s":{"a":0,"k":[100,100],"ix":3},"r":{"a":0,"k":0,"ix":6},"o":{"a":0,"k":100,"ix":7},"sk":{"a":0,"k":0,"ix":4},"sa":{"a":0,"k":0,"ix":5},"nm":"Transform"}],"nm":"Top Hole","np":2,"cix":2,"ix":1,"mn":"ADBE Vector Group","hd":false}],"ip":0,"op":60,"st":0,"bm":0},{"ddd":0,"ind":5,"ty":4,"nm":"Top","sr":1,"ks":{"o":{"a":0,"k":100,"ix":11},"r":{"a":0,"k":12,"ix":10},"p":{"a":0,"k":[805.678,324.127,0],"ix":2},"a":{"a":0,"k":[5.714,-13.952,0],"ix":1},"s":{"a":0,"k":[1400,1400,100],"ix":6}},"ao":0,"shapes":[{"ty":"gr","it":[{"ind":0,"ty":"sh","ix":1,"ks":{"a":0,"k":{"i":[[-0.18,-0.677],[3.255,-0.869],[0.257,0.955],[-3.231,0.866]],"o":[[0.259,0.955],[-3.25,0.871],[-0.183,-0.678],[3.274,-0.875]],"v":[[11.594,-15.574],[6.173,-12.269],[-0.176,-12.419],[5.247,-15.728]],"c":true},"ix":2},"nm":"Path 1","mn":"ADBE Vector Shape - Group","hd":false},{"ty":"fl","c":{"a":0,"k":[0.772549033165,0.843137264252,0.909803926945,1],"ix":4},"o":{"a":0,"k":100,"ix":5},"r":1,"nm":"Fill 1","mn":"ADBE Vector Graphic - Fill","hd":false},{"ty":"tr","p":{"a":0,"k":[0,0],"ix":2},"a":{"a":0,"k":[0,0],"ix":1},"s":{"a":0,"k":[100,100],"ix":3},"r":{"a":0,"k":0,"ix":6},"o":{"a":0,"k":100,"ix":7},"sk":{"a":0,"k":0,"ix":4},"sa":{"a":0,"k":0,"ix":5},"nm":"Transform"}],"nm":"Top","np":2,"cix":2,"ix":1,"mn":"ADBE Vector Group","hd":false}],"ip":0,"op":60,"st":0,"bm":0},{"ddd":0,"ind":6,"ty":4,"nm":"Foam","td":1,"sr":1,"ks":{"o":{"a":0,"k":100,"ix":11},"r":{"a":0,"k":12,"ix":10},"p":{"a":0,"k":[813.355,408.472,0],"ix":2},"a":{"a":0,"k":[7.503,-8.173,0],"ix":1},"s":{"a":0,"k":[1400,1400,100],"ix":6}},"ao":0,"shapes":[{"ty":"gr","it":[{"ind":0,"ty":"sh","ix":1,"ks":{"a":1,"k":[{"i":{"x":0.833,"y":0.833},"o":{"x":0.167,"y":0.167},"n":"0p833_0p833_0p167_0p167","t":0,"s":[{"i":[[-0.405,-2.28],[-4.854,1.1],[0,0],[5.704,-1.077]],"o":[[5.645,-0.927],[-0.451,-1.535],[-3.86,1.149],[0,-0.001]],"v":[[-0.547,-5.382],[15.291,-8.399],[13.341,-12.261],[-1.059,-9.079]],"c":true}],"e":[{"i":[[-0.405,-2.28],[-4.559,2.943],[0,0],[6.572,0.231]],"o":[[6.023,-0.768],[-0.451,-1.535],[-3.876,1.775],[0,-0.001]],"v":[[0.983,-7.46],[14.534,-6.12],[13.546,-9.237],[0.471,-11.157]],"c":true}]},{"i":{"x":0.833,"y":0.833},"o":{"x":0.167,"y":0.167},"n":"0p833_0p833_0p167_0p167","t":8,"s":[{"i":[[-0.405,-2.28],[-4.559,2.943],[0,0],[6.572,0.231]],"o":[[6.023,-0.768],[-0.451,-1.535],[-3.876,1.775],[0,-0.001]],"v":[[0.983,-7.46],[14.534,-6.12],[13.546,-9.237],[0.471,-11.157]],"c":true}],"e":[{"i":[[-0.405,-2.28],[-4.761,1.476],[0,0],[6.572,0.231]],"o":[[7.298,-0.353],[-0.451,-1.535],[-3.876,1.775],[0,-0.001]],"v":[[-0.041,-2.711],[14.245,-9.465],[12.892,-13.482],[-0.184,-7.946]],"c":true}]},{"i":{"x":0.833,"y":0.833},"o":{"x":0.167,"y":0.167},"n":"0p833_0p833_0p167_0p167","t":15,"s":[{"i":[[-0.405,-2.28],[-4.761,1.476],[0,0],[6.572,0.231]],"o":[[7.298,-0.353],[-0.451,-1.535],[-3.876,1.775],[0,-0.001]],"v":[[-0.041,-2.711],[14.245,-9.465],[12.892,-13.482],[-0.184,-7.946]],"c":true}],"e":[{"i":[[-0.405,-2.28],[-4.559,2.943],[0,0],[6.572,0.231]],"o":[[6.023,-0.768],[-0.451,-1.535],[-3.876,1.775],[0,-0.001]],"v":[[0.983,-7.46],[14.534,-6.12],[13.546,-9.237],[0.471,-11.157]],"c":true}]},{"i":{"x":0.833,"y":0.833},"o":{"x":0.167,"y":0.167},"n":"0p833_0p833_0p167_0p167","t":22,"s":[{"i":[[-0.405,-2.28],[-4.559,2.943],[0,0],[6.572,0.231]],"o":[[6.023,-0.768],[-0.451,-1.535],[-3.876,1.775],[0,-0.001]],"v":[[0.983,-7.46],[14.534,-6.12],[13.546,-9.237],[0.471,-11.157]],"c":true}],"e":[{"i":[[-0.405,-2.28],[-4.761,1.476],[0,0],[6.572,0.231]],"o":[[7.298,-0.353],[-0.451,-1.535],[-3.876,1.775],[0,-0.001]],"v":[[-0.231,-3.734],[14.979,-8.633],[13.626,-12.651],[-0.374,-8.968]],"c":true}]},{"i":{"x":0.833,"y":0.833},"o":{"x":0.167,"y":0.167},"n":"0p833_0p833_0p167_0p167","t":28,"s":[{"i":[[-0.405,-2.28],[-4.761,1.476],[0,0],[6.572,0.231]],"o":[[7.298,-0.353],[-0.451,-1.535],[-3.876,1.775],[0,-0.001]],"v":[[-0.231,-3.734],[14.979,-8.633],[13.626,-12.651],[-0.374,-8.968]],"c":true}],"e":[{"i":[[-0.405,-2.28],[-4.559,2.943],[0,0],[6.572,0.231]],"o":[[6.023,-0.768],[-0.451,-1.535],[-3.876,1.775],[0,-0.001]],"v":[[-0.916,-5.742],[15.291,-8.399],[14.303,-11.516],[-1.428,-9.439]],"c":true}]},{"i":{"x":0.833,"y":0.833},"o":{"x":0.167,"y":0.167},"n":"0p833_0p833_0p167_0p167","t":36,"s":[{"i":[[-0.405,-2.28],[-4.559,2.943],[0,0],[6.572,0.231]],"o":[[6.023,-0.768],[-0.451,-1.535],[-3.876,1.775],[0,-0.001]],"v":[[-0.916,-5.742],[15.291,-8.399],[14.303,-11.516],[-1.428,-9.439]],"c":true}],"e":[{"i":[[-0.405,-2.28],[-4.854,1.1],[0,0],[5.704,-1.077]],"o":[[5.645,-0.927],[-0.451,-1.535],[-3.86,1.149],[0,-0.001]],"v":[[-0.547,-5.382],[15.291,-8.399],[13.341,-12.261],[-1.059,-9.079]],"c":true}]},{"t":42}],"ix":2},"nm":"Path 1","mn":"ADBE Vector Shape - Group","hd":false},{"ty":"fl","c":{"a":0,"k":[1,0.909803926945,0.733333349228,1],"ix":4},"o":{"a":0,"k":100,"ix":5},"r":1,"nm":"Fill 1","mn":"ADBE Vector Graphic - Fill","hd":false},{"ty":"tr","p":{"a":0,"k":[0,0],"ix":2},"a":{"a":0,"k":[0,0],"ix":1},"s":{"a":0,"k":[100,100],"ix":3},"r":{"a":0,"k":0,"ix":6},"o":{"a":0,"k":100,"ix":7},"sk":{"a":0,"k":0,"ix":4},"sa":{"a":0,"k":0,"ix":5},"nm":"Transform"}],"nm":"Foam","np":2,"cix":2,"ix":1,"mn":"ADBE Vector Group","hd":false}],"ip":0,"op":60,"st":0,"bm":0},{"ddd":0,"ind":7,"ty":4,"nm":"Shape Layer 1","tt":1,"sr":1,"ks":{"o":{"a":0,"k":100,"ix":11},"r":{"a":0,"k":0,"ix":10},"p":{"a":0,"k":[512,512,0],"ix":2},"a":{"a":0,"k":[0,0,0],"ix":1},"s":{"a":0,"k":[100,100,100],"ix":6}},"ao":0,"shapes":[{"ty":"gr","it":[{"ind":0,"ty":"sh","ix":1,"ks":{"a":0,"k":{"i":[[-16.568,-48.612],[0,0],[5.341,60.848],[-3,15]],"o":[[19.086,56],[0,0],[-5,-56.961],[10.072,-50.36]],"v":[[95.457,-82.48],[118.457,100.481],[-64.457,89.48],[-60.207,-74.48]],"c":true},"ix":2},"nm":"Path 1","mn":"ADBE Vector Shape - Group","hd":false},{"ty":"fl","c":{"a":0,"k":[1,0.909803926945,0.733333349228,1],"ix":4},"o":{"a":0,"k":100,"ix":5},"r":1,"nm":"Fill 2","mn":"ADBE Vector Graphic - Fill","hd":false},{"ty":"tr","p":{"a":0,"k":[276.457,-101.52],"ix":2},"a":{"a":0,"k":[0,0],"ix":1},"s":{"a":0,"k":[100,100],"ix":3},"r":{"a":0,"k":0,"ix":6},"o":{"a":0,"k":100,"ix":7},"sk":{"a":0,"k":0,"ix":4},"sa":{"a":0,"k":0,"ix":5},"nm":"Transform"}],"nm":"Rectangle 1","np":2,"cix":2,"ix":1,"mn":"ADBE Vector Group","hd":false}],"ip":0,"op":60,"st":0,"bm":0},{"ddd":0,"ind":8,"ty":4,"nm":"Glass Shadow","sr":1,"ks":{"o":{"a":0,"k":100,"ix":11},"r":{"a":0,"k":12,"ix":10},"p":{"a":0,"k":[828.925,696.34,0],"ix":2},"a":{"a":0,"k":[12.865,11.708,0],"ix":1},"s":{"a":0,"k":[1400,1400,100],"ix":6}},"ao":0,"shapes":[{"ty":"gr","it":[{"ind":0,"ty":"sh","ix":1,"ks":{"a":0,"k":{"i":[[0.111,0.416],[1.746,-0.623],[-0.094,-0.356],[-0.683,0.188]],"o":[[-0.069,-0.264],[-1.17,0.418],[0.039,0.152],[0.72,-0.191]],"v":[[15.132,10.498],[12.37,12.029],[10.602,12.457],[12.891,12.914]],"c":true},"ix":2},"nm":"Path 1","mn":"ADBE Vector Shape - Group","hd":false},{"ty":"fl","c":{"a":0,"k":[0.600000023842,0.658823549747,0.68235296011,1],"ix":4},"o":{"a":0,"k":100,"ix":5},"r":1,"nm":"Fill 1","mn":"ADBE Vector Graphic - Fill","hd":false},{"ty":"tr","p":{"a":0,"k":[0,0],"ix":2},"a":{"a":0,"k":[0,0],"ix":1},"s":{"a":0,"k":[100,100],"ix":3},"r":{"a":0,"k":0,"ix":6},"o":{"a":0,"k":100,"ix":7},"sk":{"a":0,"k":0,"ix":4},"sa":{"a":0,"k":0,"ix":5},"nm":"Transform"}],"nm":"Glass Shadow","np":2,"cix":2,"ix":1,"mn":"ADBE Vector Group","hd":false}],"ip":0,"op":60,"st":0,"bm":0},{"ddd":0,"ind":9,"ty":4,"nm":"Liquid","sr":1,"ks":{"o":{"a":0,"k":100,"ix":11},"r":{"a":0,"k":12,"ix":10},"p":{"a":0,"k":[799.037,533.009,0],"ix":2},"a":{"a":0,"k":[8.352,0.74,0],"ix":1},"s":{"a":0,"k":[1400,1400,100],"ix":6}},"ao":0,"shapes":[{"ty":"gr","it":[{"ind":0,"ty":"sh","ix":1,"ks":{"a":1,"k":[{"i":{"x":0.833,"y":0.833},"o":{"x":0.167,"y":0.167},"n":"0p833_0p833_0p167_0p167","t":12,"s":[{"i":[[1.242,10.254],[-10.256,-0.443],[4.963,-1.332]],"o":[[0,0],[2.708,8.539],[-5.83,1.559]],"v":[[0.761,-9.479],[13.927,-8.162],[12.335,10.746]],"c":true}],"e":[{"i":[[1.242,10.254],[-9.281,1.846],[4.963,-1.332]],"o":[[0,0],[3.088,8.915],[-5.83,1.559]],"v":[[1.054,-7.748],[13.532,-9.418],[12.335,10.746]],"c":true}]},{"i":{"x":0.833,"y":0.833},"o":{"x":0.167,"y":0.167},"n":"0p833_0p833_0p167_0p167","t":15,"s":[{"i":[[1.242,10.254],[-9.281,1.846],[4.963,-1.332]],"o":[[0,0],[3.088,8.915],[-5.83,1.559]],"v":[[1.054,-7.748],[13.532,-9.418],[12.335,10.746]],"c":true}],"e":[{"i":[[1.242,10.254],[-10.256,-0.443],[4.963,-1.332]],"o":[[0,0],[2.708,8.539],[-5.83,1.559]],"v":[[0.761,-9.479],[13.927,-8.162],[12.335,10.746]],"c":true}]},{"i":{"x":0.833,"y":0.833},"o":{"x":0.167,"y":0.167},"n":"0p833_0p833_0p167_0p167","t":23,"s":[{"i":[[1.242,10.254],[-10.256,-0.443],[4.963,-1.332]],"o":[[0,0],[2.708,8.539],[-5.83,1.559]],"v":[[0.761,-9.479],[13.927,-8.162],[12.335,10.746]],"c":true}],"e":[{"i":[[1.242,10.254],[-10.256,-0.443],[4.963,-1.332]],"o":[[0,0],[2.708,8.539],[-5.83,1.559]],"v":[[0.859,-8.854],[13.927,-8.162],[12.335,10.746]],"c":true}]},{"i":{"x":0.833,"y":0.833},"o":{"x":0.167,"y":0.167},"n":"0p833_0p833_0p167_0p167","t":29,"s":[{"i":[[1.242,10.254],[-10.256,-0.443],[4.963,-1.332]],"o":[[0,0],[2.708,8.539],[-5.83,1.559]],"v":[[0.859,-8.854],[13.927,-8.162],[12.335,10.746]],"c":true}],"e":[{"i":[[1.242,10.254],[-10.256,-0.443],[4.963,-1.332]],"o":[[0,0],[2.708,8.539],[-5.83,1.559]],"v":[[0.761,-9.479],[13.927,-8.162],[12.335,10.746]],"c":true}]},{"t":33}],"ix":2},"nm":"Path 1","mn":"ADBE Vector Shape - Group","hd":false},{"ty":"gf","o":{"a":0,"k":100,"ix":10},"r":1,"g":{"p":9,"k":{"a":0,"k":[0,1,0.784,0.278,0.028,1,0.79,0.288,0.056,1,0.796,0.298,0.227,1,0.827,0.341,0.397,1,0.859,0.384,0.558,1,0.878,0.412,0.719,1,0.898,0.439,0.86,1,0.904,0.449,1,1,0.91,0.459],"ix":9}},"s":{"a":0,"k":[12.414,10.805],"ix":5},"e":{"a":0,"k":[5.48,-11.736],"ix":6},"t":1,"nm":"liquidgradientzazea","mn":"ADBE Vector Graphic - G-Fill","hd":false},{"ty":"tr","p":{"a":0,"k":[0,0],"ix":2},"a":{"a":0,"k":[0,0],"ix":1},"s":{"a":0,"k":[100,100],"ix":3},"r":{"a":0,"k":0,"ix":6},"o":{"a":0,"k":100,"ix":7},"sk":{"a":0,"k":0,"ix":4},"sa":{"a":0,"k":0,"ix":5},"nm":"Transform"}],"nm":"Liquid","np":2,"cix":2,"ix":1,"mn":"ADBE Vector Group","hd":false}],"ip":0,"op":60,"st":0,"bm":0},{"ddd":0,"ind":10,"ty":4,"nm":"Glass top bg","sr":1,"ks":{"o":{"a":0,"k":100,"ix":11},"r":{"a":0,"k":12,"ix":10},"p":{"a":0,"k":[811.038,466.892,0],"ix":2},"a":{"a":0,"k":[8.208,-4.057,0],"ix":1},"s":{"a":0,"k":[1400,1400,100],"ix":6}},"ao":0,"shapes":[{"ty":"gr","it":[{"ind":0,"ty":"sh","ix":1,"ks":{"a":0,"k":{"i":[[0.262,3.123],[-1.139,0.318],[-1.273,-0.836],[-1.244,-11.217],[0,0]],"o":[[0.682,-1.35],[1.141,-0.291],[0.214,0.16],[0,0],[-4.744,-6.94]],"v":[[0.423,-12.531],[5.353,-15.32],[11.025,-15.365],[15.994,2.342],[6.41,7.68]],"c":true},"ix":2},"nm":"Path 1","mn":"ADBE Vector Shape - Group","hd":false},{"ty":"fl","c":{"a":0,"k":[0.901960790157,0.921568632126,0.937254905701,1],"ix":4},"o":{"a":0,"k":100,"ix":5},"r":1,"nm":"Fill 1","mn":"ADBE Vector Graphic - Fill","hd":false},{"ty":"tr","p":{"a":0,"k":[0,0],"ix":2},"a":{"a":0,"k":[0,0],"ix":1},"s":{"a":0,"k":[100,100],"ix":3},"r":{"a":0,"k":0,"ix":6},"o":{"a":0,"k":100,"ix":7},"sk":{"a":0,"k":0,"ix":4},"sa":{"a":0,"k":0,"ix":5},"nm":"Transform"}],"nm":"Glass top bg","np":2,"cix":2,"ix":1,"mn":"ADBE Vector Group","hd":false}],"ip":0,"op":60,"st":0,"bm":0},{"ddd":0,"ind":11,"ty":4,"nm":"Glass top","sr":1,"ks":{"o":{"a":0,"k":100,"ix":11},"r":{"a":0,"k":12,"ix":10},"p":{"a":0,"k":[805.817,507.092,0],"ix":2},"a":{"a":0,"k":[8.44,-1.171,0],"ix":1},"s":{"a":0,"k":[1400,1400,100],"ix":6}},"ao":0,"shapes":[{"ty":"gr","it":[{"ind":0,"ty":"sh","ix":1,"ks":{"a":0,"k":{"i":[[0.688,0.437],[0.959,-1.853],[-11.081,-0.289]],"o":[[-1.757,-1.121],[-0.381,0.721],[9.45,-5.791]],"v":[[11.469,-15.759],[-0.159,-12.644],[13.135,13.705]],"c":true},"ix":2},"nm":"Path 1","mn":"ADBE Vector Shape - Group","hd":false},{"ty":"fl","c":{"a":0,"k":[0.772549033165,0.843137264252,0.909803926945,1],"ix":4},"o":{"a":0,"k":100,"ix":5},"r":1,"nm":"Fill 1","mn":"ADBE Vector Graphic - Fill","hd":false},{"ty":"tr","p":{"a":0,"k":[0,0],"ix":2},"a":{"a":0,"k":[0,0],"ix":1},"s":{"a":0,"k":[100,100],"ix":3},"r":{"a":0,"k":0,"ix":6},"o":{"a":0,"k":100,"ix":7},"sk":{"a":0,"k":0,"ix":4},"sa":{"a":0,"k":0,"ix":5},"nm":"Transform"}],"nm":"Glass top","np":2,"cix":2,"ix":1,"mn":"ADBE Vector Group","hd":false}],"ip":0,"op":60,"st":0,"bm":0},{"ddd":0,"ind":12,"ty":4,"nm":"Bot Highlight","sr":1,"ks":{"o":{"a":0,"k":100,"ix":11},"r":{"a":0,"k":12,"ix":10},"p":{"a":0,"k":[806.361,931.192,0],"ix":2},"a":{"a":0,"k":[14.777,28.452,0],"ix":1},"s":{"a":0,"k":[1400,1400,100],"ix":6}},"ao":0,"shapes":[{"ty":"gr","it":[{"ind":0,"ty":"sh","ix":1,"ks":{"a":0,"k":{"i":[[-3.726,0.996],[-2.173,1.776],[-0.129,-0.473]],"o":[[4.516,-1.209],[1.771,-1.453],[0.14,0.531]],"v":[[17.417,28.6],[13.146,27.967],[11.037,29.098]],"c":true},"ix":2},"nm":"Path 1","mn":"ADBE Vector Shape - Group","hd":false},{"ty":"fl","c":{"a":0,"k":[0.901960790157,0.921568632126,0.937254905701,1],"ix":4},"o":{"a":0,"k":100,"ix":5},"r":1,"nm":"Fill 1","mn":"ADBE Vector Graphic - Fill","hd":false},{"ty":"tr","p":{"a":0,"k":[0,0],"ix":2},"a":{"a":0,"k":[0,0],"ix":1},"s":{"a":0,"k":[100,100],"ix":3},"r":{"a":0,"k":0,"ix":6},"o":{"a":0,"k":100,"ix":7},"sk":{"a":0,"k":0,"ix":4},"sa":{"a":0,"k":0,"ix":5},"nm":"Transform"}],"nm":"Bot Highlight","np":2,"cix":2,"ix":1,"mn":"ADBE Vector Group","hd":false}],"ip":0,"op":60,"st":0,"bm":0},{"ddd":0,"ind":13,"ty":4,"nm":"Bot","sr":1,"ks":{"o":{"a":0,"k":100,"ix":11},"r":{"a":0,"k":12,"ix":10},"p":{"a":0,"k":[856.592,835.558,0],"ix":2},"a":{"a":0,"k":[16.866,21.024,0],"ix":1},"s":{"a":0,"k":[1400,1400,100],"ix":6}},"ao":0,"shapes":[{"ty":"gr","it":[{"ind":0,"ty":"sh","ix":1,"ks":{"a":0,"k":{"i":[[-2.403,0.875],[1.133,4.231],[0,0],[0,0],[-1.801,-6.724],[-1.296,-0.891],[-0.175,-0.652],[3.661,-0.98],[0.226,0.852]],"o":[[0.671,-1.422],[-1.801,-6.723],[0,0],[0,0],[1.132,4.229],[2.52,-0.432],[0.227,0.855],[-3.659,0.986],[-0.175,-0.659]],"v":[[14.388,26.752],[14.005,20.037],[10.749,13.17],[14.926,12.049],[15.542,19.627],[18.565,25.627],[23.487,25.869],[17.277,29.187],[10.243,29.421]],"c":true},"ix":2},"nm":"Path 1","mn":"ADBE Vector Shape - Group","hd":false},{"ty":"fl","c":{"a":0,"k":[0.772549033165,0.843137264252,0.909803926945,1],"ix":4},"o":{"a":0,"k":100,"ix":5},"r":1,"nm":"Fill 1","mn":"ADBE Vector Graphic - Fill","hd":false},{"ty":"tr","p":{"a":0,"k":[0,0],"ix":2},"a":{"a":0,"k":[0,0],"ix":1},"s":{"a":0,"k":[100,100],"ix":3},"r":{"a":0,"k":0,"ix":6},"o":{"a":0,"k":100,"ix":7},"sk":{"a":0,"k":0,"ix":4},"sa":{"a":0,"k":0,"ix":5},"nm":"Transform"}],"nm":"Bot","np":2,"cix":2,"ix":1,"mn":"ADBE Vector Group","hd":false}],"ip":0,"op":60,"st":0,"bm":0}]}],"layers":[{"ddd":0,"ind":1,"ty":3,"nm":"Scale Control","sr":1,"ks":{"o":{"a":0,"k":0,"ix":11},"r":{"a":0,"k":0,"ix":10},"p":{"a":0,"k":[468,442,0],"ix":2},"a":{"a":0,"k":[0,0,0],"ix":1},"s":{"a":0,"k":[1400,1400,100],"ix":6}},"ao":0,"ip":0,"op":60,"st":0,"bm":0},{"ddd":0,"ind":2,"ty":4,"nm":"Clink 2","parent":1,"sr":1,"ks":{"o":{"a":1,"k":[{"i":{"x":[0.667],"y":[1]},"o":{"x":[0.333],"y":[0]},"n":["0p667_1_0p333_0"],"t":24,"s":[100],"e":[0]},{"t":39}],"ix":11},"r":{"a":0,"k":44,"ix":10},"p":{"a":0,"k":[3.639,-19.412,0],"ix":2},"a":{"a":0,"k":[-18.505,-16.676,0],"ix":1},"s":{"a":0,"k":[75.357,75.357,100],"ix":6}},"ao":0,"shapes":[{"ty":"gr","it":[{"ind":0,"ty":"sh","ix":1,"ks":{"a":1,"k":[{"i":{"x":0.385,"y":1},"o":{"x":0.167,"y":0.167},"n":"0p385_1_0p167_0p167","t":15,"s":[{"i":[[3.587,-2.071],[-0.282,0.163]],"o":[[-3.588,2.071],[0.285,-0.165]],"v":[[-20.458,-27.687],[-15.67,-19.391]],"c":true}],"e":[{"i":[[3.587,-2.071],[-0.282,0.163]],"o":[[-3.588,2.071],[0.285,-0.165]],"v":[[-25.758,-37.987],[-20.97,-29.691]],"c":true}]},{"t":23}],"ix":2},"nm":"Path 1","mn":"ADBE Vector Shape - Group","hd":false},{"ty":"fl","c":{"a":0,"k":[0.058823529412,0.705882352941,0.83137254902,1],"ix":4},"o":{"a":0,"k":100,"ix":5},"r":1,"nm":"Fill 1","mn":"ADBE Vector Graphic - Fill","hd":false},{"ty":"tr","p":{"a":0,"k":[-13.853,-8.743],"ix":2},"a":{"a":0,"k":[-13.853,-15.743],"ix":1},"s":{"a":0,"k":[100,100],"ix":3},"r":{"a":0,"k":26,"ix":6},"o":{"a":0,"k":100,"ix":7},"sk":{"a":0,"k":0,"ix":4},"sa":{"a":0,"k":0,"ix":5},"nm":"Transform"}],"nm":"Group 3","np":2,"cix":2,"ix":1,"mn":"ADBE Vector Group","hd":false},{"ty":"gr","it":[{"ind":0,"ty":"sh","ix":1,"ks":{"a":1,"k":[{"i":{"x":0.385,"y":1},"o":{"x":0.167,"y":0.167},"n":"0p385_1_0p167_0p167","t":15,"s":[{"i":[[3.587,-2.071],[-0.282,0.163]],"o":[[-3.588,2.071],[0.285,-0.165]],"v":[[-20.458,-27.687],[-15.67,-19.391]],"c":true}],"e":[{"i":[[3.587,-2.071],[-0.282,0.163]],"o":[[-3.588,2.071],[0.285,-0.165]],"v":[[-25.758,-37.987],[-20.97,-29.691]],"c":true}]},{"t":23}],"ix":2},"nm":"Path 1","mn":"ADBE Vector Shape - Group","hd":false},{"ty":"fl","c":{"a":0,"k":[0.058823529412,0.705882352941,0.83137254902,1],"ix":4},"o":{"a":0,"k":100,"ix":5},"r":1,"nm":"Fill 1","mn":"ADBE Vector Graphic - Fill","hd":false},{"ty":"tr","p":{"a":0,"k":[-13.853,-8.743],"ix":2},"a":{"a":0,"k":[-13.853,-15.743],"ix":1},"s":{"a":0,"k":[100,100],"ix":3},"r":{"a":0,"k":-26,"ix":6},"o":{"a":0,"k":100,"ix":7},"sk":{"a":0,"k":0,"ix":4},"sa":{"a":0,"k":0,"ix":5},"nm":"Transform"}],"nm":"Group 2","np":2,"cix":2,"ix":2,"mn":"ADBE Vector Group","hd":false},{"ty":"gr","it":[{"ind":0,"ty":"sh","ix":1,"ks":{"a":1,"k":[{"i":{"x":0.385,"y":1},"o":{"x":0.167,"y":0.167},"n":"0p385_1_0p167_0p167","t":15,"s":[{"i":[[3.587,-2.071],[-0.282,0.163]],"o":[[-3.588,2.071],[0.285,-0.165]],"v":[[-20.458,-27.687],[-15.67,-19.391]],"c":true}],"e":[{"i":[[3.587,-2.071],[-0.282,0.163]],"o":[[-3.588,2.071],[0.285,-0.165]],"v":[[-25.758,-37.987],[-20.97,-29.691]],"c":true}]},{"t":23}],"ix":2},"nm":"Path 1","mn":"ADBE Vector Shape - Group","hd":false},{"ty":"fl","c":{"a":0,"k":[0.058823529412,0.705882352941,0.83137254902,1],"ix":4},"o":{"a":0,"k":100,"ix":5},"r":1,"nm":"Fill 1","mn":"ADBE Vector Graphic - Fill","hd":false},{"ty":"tr","p":{"a":0,"k":[-13.853,-8.743],"ix":2},"a":{"a":0,"k":[-13.853,-15.743],"ix":1},"s":{"a":0,"k":[100,100],"ix":3},"r":{"a":0,"k":0,"ix":6},"o":{"a":0,"k":100,"ix":7},"sk":{"a":0,"k":0,"ix":4},"sa":{"a":0,"k":0,"ix":5},"nm":"Transform"}],"nm":"Group 1","np":2,"cix":2,"ix":3,"mn":"ADBE Vector Group","hd":false}],"ip":15,"op":39,"st":0,"bm":0},{"ddd":0,"ind":3,"ty":3,"nm":"Right Mug Control","parent":1,"sr":1,"ks":{"o":{"a":0,"k":0,"ix":11},"r":{"a":1,"k":[{"i":{"x":[0.667],"y":[1.043]},"o":{"x":[0.333],"y":[0]},"n":["0p667_1p043_0p333_0"],"t":0,"s":[27],"e":[1.332]},{"i":{"x":[0.667],"y":[1]},"o":{"x":[0.333],"y":[0.032]},"n":["0p667_1_0p333_0p032"],"t":10,"s":[1.332],"e":[29]},{"i":{"x":[0.667],"y":[1]},"o":{"x":[0.333],"y":[0]},"n":["0p667_1_0p333_0"],"t":18,"s":[29],"e":[29]},{"i":{"x":[0.395],"y":[1]},"o":{"x":[0.333],"y":[0]},"n":["0p395_1_0p333_0"],"t":34,"s":[29],"e":[37]},{"i":{"x":[0.667],"y":[1]},"o":{"x":[0.333],"y":[0]},"n":["0p667_1_0p333_0"],"t":38,"s":[37],"e":[27]},{"t":54}],"ix":10},"p":{"a":1,"k":[{"i":{"x":0.827,"y":0.92},"o":{"x":0.859,"y":0},"n":"0p827_0p92_0p859_0","t":0,"s":[25.429,-5.531,0],"e":[11.714,-7.102,0],"to":[-6.7142858505249,8.59523773193359,0],"ti":[-0.9679006934166,5.31098794937134,0]},{"i":{"x":0.979,"y":0},"o":{"x":0.021,"y":1},"n":"0p979_0_0p021_1","t":18,"s":[11.714,-7.102,0],"e":[11.714,-7.102,0],"to":[0.0551350787282,0.10412359982729,0],"ti":[0.10352788120508,0.02527359686792,0]},{"i":{"x":0.486,"y":1},"o":{"x":0.333,"y":0.163},"n":"0p486_1_0p333_0p163","t":34,"s":[11.714,-7.102,0],"e":[25.429,-5.531,0],"to":[1.12656366825104,-6.18159055709839,0],"ti":[-1.29798924922943,-4.52734613418579,0]},{"t":51}],"ix":2},"a":{"a":0,"k":[217.029,34.721,0],"ix":1},"s":{"a":0,"k":[5.102,5.102,100],"ix":6}},"ao":0,"ip":0,"op":70,"st":0,"bm":0},{"ddd":0,"ind":4,"ty":3,"nm":"Left Mug Control","parent":1,"sr":1,"ks":{"o":{"a":0,"k":0,"ix":11},"r":{"a":1,"k":[{"i":{"x":[0.667],"y":[1]},"o":{"x":[0.333],"y":[0]},"n":["0p667_1_0p333_0"],"t":0,"s":[2],"e":[15]},{"i":{"x":[0.667],"y":[1]},"o":{"x":[0.333],"y":[0]},"n":["0p667_1_0p333_0"],"t":10,"s":[15],"e":[-5.465]},{"i":{"x":[0.667],"y":[1]},"o":{"x":[0.333],"y":[0]},"n":["0p667_1_0p333_0"],"t":18,"s":[-5.465],"e":[-5.465]},{"i":{"x":[0.675],"y":[2.708]},"o":{"x":[0.333],"y":[0]},"n":["0p675_2p708_0p333_0"],"t":35,"s":[-5.465],"e":[-5.465]},{"i":{"x":[0.667],"y":[1]},"o":{"x":[0.337],"y":[-0.305]},"n":["0p667_1_0p337_-0p305"],"t":42,"s":[-5.465],"e":[2]},{"t":51}],"ix":10},"p":{"a":1,"k":[{"i":{"x":0.795,"y":0.867},"o":{"x":0.669,"y":0},"n":"0p795_0p867_0p669_0","t":0,"s":[-23.694,1.735,0],"e":[-14.939,-1.643,0],"to":[2.98299312591553,5.94897937774658,0],"ti":[4.77551031112671,8.9285717010498,0]},{"i":{"x":0.989,"y":0},"o":{"x":0.011,"y":1},"n":"0p989_0_0p011_1","t":18,"s":[-14.939,-1.643,0],"e":[-14.939,-1.643,0],"to":[0.04591805487871,0.07142857462168,0],"ti":[0.02551051601768,0.07142857462168,0]},{"i":{"x":0.486,"y":1},"o":{"x":0.333,"y":0.245},"n":"0p486_1_0p333_0p245","t":35,"s":[-14.939,-1.643,0],"e":[-23.694,1.735,0],"to":[-1.84693908691406,-2.57142853736877,0],"ti":[0.10086222738028,-5.41620397567749,0]},{"t":48}],"ix":2},"a":{"a":0,"k":[-126.129,54.297,0],"ix":1},"s":{"a":0,"k":[5.102,5.102,100],"ix":6}},"ao":0,"ip":0,"op":70,"st":0,"bm":0},{"ddd":0,"ind":6,"ty":0,"nm":"Left Glass","parent":4,"refId":"comp_0","sr":1,"ks":{"o":{"a":0,"k":100,"ix":11},"r":{"a":0,"k":0,"ix":10},"p":{"a":0,"k":[-384.129,20.297,0],"ix":2},"a":{"a":0,"k":[512,512,0],"ix":1},"s":{"a":0,"k":[140,140,100],"ix":6}},"ao":0,"w":1024,"h":1024,"ip":0,"op":60,"st":0,"bm":0},{"ddd":0,"ind":7,"ty":0,"nm":"Right Glass","parent":3,"refId":"comp_1","sr":1,"ks":{"o":{"a":0,"k":100,"ix":11},"r":{"a":0,"k":-25,"ix":10},"p":{"a":0,"k":[-183.788,341.231,0],"ix":2},"a":{"a":0,"k":[512,512,0],"ix":1},"s":{"a":0,"k":[140,140,100],"ix":6}},"ao":0,"w":1024,"h":1024,"ip":0,"op":60,"st":0,"bm":0}],"markers":[]}